qcs_sdk_python-0.21.22.dist-info/METADATA
qcs_sdk_python-0.21.22.dist-info/WHEEL
qcs_sdk/__init__.pyi
qcs_sdk/qpu/__init__.pyi
qcs_sdk/qpu/api.pyi
qcs_sdk/qpu/translation.pyi
qcs_sdk/qpu/experimental/__init__.pyi
qcs_sdk/qpu/experimental/random.pyi
qcs_sdk/qpu/__init__.py
qcs_sdk/qpu/isa.pyi
qcs_sdk/_tracing_subscriber/__init__.pyi
qcs_sdk/_tracing_subscriber/layers/file/__init__.pyi
qcs_sdk/_tracing_subscriber/layers/file/__init__.py
qcs_sdk/_tracing_subscriber/layers/__init__.pyi
qcs_sdk/_tracing_subscriber/layers/otel_otlp/__init__.pyi
qcs_sdk/_tracing_subscriber/layers/otel_otlp/__init__.py
qcs_sdk/_tracing_subscriber/layers/otel_otlp_file/__init__.pyi
qcs_sdk/_tracing_subscriber/layers/otel_otlp_file/__init__.py
qcs_sdk/_tracing_subscriber/layers/__init__.py
qcs_sdk/_tracing_subscriber/common/__init__.pyi
qcs_sdk/_tracing_subscriber/common/__init__.py
qcs_sdk/_tracing_subscriber/.stubtest-allowlist
qcs_sdk/_tracing_subscriber/subscriber/__init__.pyi
qcs_sdk/_tracing_subscriber/subscriber/__init__.py
qcs_sdk/_tracing_subscriber/__init__.py
qcs_sdk/qvm/__init__.pyi
qcs_sdk/qvm/api.pyi
qcs_sdk/qvm/__init__.py
qcs_sdk/py.typed
qcs_sdk/client.pyi
qcs_sdk/client.py
qcs_sdk/__init__.py
qcs_sdk/compiler/__init__.pyi
qcs_sdk/compiler/quilc.pyi
qcs_sdk/compiler/__init__.py
qcs_sdk/diagnostics.py
THIRDPARTY.yaml
qcs_sdk/qcs_sdk.cpython-310-x86_64-linux-gnu.so
qcs_sdk_python-0.21.22.dist-info/RECORD
