Metadata-Version: 2.4
Name: qcs-sdk-python
Version: 0.21.22
Classifier: Development Status :: 3 - Alpha
Classifier: License :: OSI Approved :: Apache Software License
Classifier: Programming Language :: Python :: 3.8
Classifier: Programming Language :: Python :: 3.9
Classifier: Programming Language :: Python :: 3.10
Classifier: Programming Language :: Python :: 3.11
Classifier: Operating System :: OS Independent
Requires-Dist: quil>=0.15.2
Requires-Dist: qcs-api-client-common>=0.11.8
Requires-Dist: pyquil==4.14.2 ; extra == 'pyquil'
Requires-Dist: black>=24.8.0 ; extra == 'dev'
Requires-Dist: opentelemetry-sdk==1.25.0 ; extra == 'dev'
Requires-Dist: pytest>=8.1.1 ; extra == 'dev'
Requires-Dist: pytest-asyncio>=0.23.6 ; extra == 'dev'
Requires-Dist: pytest-mock>=3.14.0 ; extra == 'dev'
Requires-Dist: pytest-sugar>=1.0.0 ; extra == 'dev'
Requires-Dist: pytest-clarity>=1.0.1 ; extra == 'dev'
Requires-Dist: syrupy>=4.0.0 ; extra == 'dev'
Requires-Dist: maturin==1.8.2 ; extra == 'dev'
Requires-Dist: numpy>=1.24.1 ; extra == 'dev'
Requires-Dist: pdoc>=14.6.1 ; extra == 'dev'
Requires-Dist: ruff>=0.3.5 ; extra == 'dev'
Requires-Dist: mypy>=1.14.1 ; extra == 'dev'
Provides-Extra: pyquil
Provides-Extra: dev
Summary: Python interface for the QCS Rust SDK
Keywords: pyquil,SDK,Rigetti,Quil,Quantum
Author-email: Rigetti Computing <softapps@rigetti.com>, Mark Skilbeck <mark.skilbeck@rigetti.com>, Marquess Valdez <mvaldez@rigetti.com>, Randall Fulton <rfulton@rigetti.com>
License: Apache-2.0
Project-URL: Source Code, https://github.com/rigetti/qcs-sdk-rust
